jsspetri/__init__.py
jsspetri/envs/common/__init__.py
jsspetri/envs/common/build_blocks.py
jsspetri/envs/common/instance_loader.py
jsspetri/envs/common/petri_build.py
jsspetri/envs/common/instances/rta00
jsspetri/envs/common/instances/rta01
jsspetri/envs/common/instances/rta02
jsspetri/envs/common/instances/rta03
jsspetri/envs/common/instances/rta04
jsspetri/envs/common/instances/rta05
jsspetri/envs/common/instances/rta06
jsspetri/envs/common/instances/rta07
jsspetri/envs/common/instances/rta08
jsspetri/envs/common/instances/rta09
jsspetri/envs/common/instances/rta10
jsspetri/envs/common/instances/rta11
jsspetri/envs/common/instances/rta12
jsspetri/envs/common/instances/rta13
jsspetri/envs/common/instances/rta14
jsspetri/envs/common/instances/rta15
jsspetri/envs/common/instances/rta16
jsspetri/envs/common/instances/rta17
jsspetri/envs/common/instances/rta18
jsspetri/envs/common/instances/rta19
jsspetri/envs/common/instances/rta20
jsspetri/envs/common/instances/rta21
jsspetri/envs/common/instances/rta22
jsspetri/envs/common/instances/rta23
jsspetri/envs/common/instances/rta24
jsspetri/envs/common/instances/rta25
jsspetri/envs/common/instances/rta26
jsspetri/envs/common/instances/rta27
jsspetri/envs/common/instances/rta28
jsspetri/envs/common/instances/rta29
jsspetri/envs/common/instances/rta30
jsspetri/envs/common/instances/rta31
jsspetri/envs/common/instances/rta32
jsspetri/envs/common/instances/rta33
jsspetri/envs/common/instances/rta34
jsspetri/envs/common/instances/rta35
jsspetri/envs/common/instances/rta36
jsspetri/envs/common/instances/rta37
jsspetri/envs/common/instances/rta38
jsspetri/envs/common/instances/rta39
jsspetri/envs/common/instances/rta40
jsspetri/envs/common/instances/rta41
jsspetri/envs/common/instances/rta42
jsspetri/envs/common/instances/rta43
jsspetri/envs/common/instances/rta44
jsspetri/envs/common/instances/rta45
jsspetri/envs/common/instances/rta46
jsspetri/envs/common/instances/rta47
jsspetri/envs/common/instances/rta48
jsspetri-1.0.4.dist-info/METADATA
jsspetri-1.0.4.dist-info/WHEEL
jsspetri-1.0.4.dist-info/top_level.txt
jsspetri-1.0.4.dist-info/RECORD
