Metadata-Version: 2.1
Name: jsspetri
Version: 1.0.4
Summary: JSSPetri: Job Shop Scheduling with Petri Nets and Reinforcement learning multi ojective support
Home-page: https://www.fh-swf.de/de/forschung___transfer_4/labore_3/labs/labor_fuer_automatisierungstechnik__soest_1/standardseite_57.php
Author: Sofiene Lassoued
Author-email: lassoued.sofiene@fh-swf.de
Project-URL: Documentation, https://arxiv.org/abs/2402.00046
Project-URL: Repository, https://github.com/Sofiene-Uni/jsspetri
Requires-Dist: gymnasium
Requires-Dist: pandas
Requires-Dist: numpy
